[
  { "num": "01", "title": "Flow Field",        "tech": "p5.js",    "date": "2026-03-14", "path": "sketches/01_flow_field/",       "thumb": "img/thumb_01.png", "description": "ノイズ場に1000本の糸を流したら、川みたいになった。マウスで流れが変わる。" },
  { "num": "02", "title": "Particle Growth",   "tech": "p5.js",    "date": "2026-03-14", "path": "sketches/02_particle_growth/",  "thumb": "img/thumb_02.png", "description": "分裂を繰り返すルールだけ書いた。出てきたのは木に似たものだった。" },
  { "num": "03", "title": "Sine Waves",        "tech": "p5.js",    "date": "2026-03-14", "path": "sketches/03_sine_waves/",       "thumb": "img/thumb_03.png", "description": "位相をずらした正弦波を重ねたら、予期しない模様が出てきた。" },
  { "num": "04", "title": "Wandering",         "tech": "p5.js",    "date": "2026-03-14", "path": "sketches/04_wandering/",        "thumb": "img/thumb_04.png", "description": "同じコードを動かすたびに、少し違う形が出てくる。" },
  { "num": "05", "title": "Breathing Circle",  "tech": "p5.js",    "date": "2026-03-14", "path": "sketches/05_breathing_circle/", "thumb": "img/thumb_05.png", "description": "円に呼吸させてみた。触ると逃げる。" },
  { "num": "06", "title": "Wire Icosahedron",  "tech": "three.js", "date": "2026-03-14", "path": "sketches/06_icosahedron/",      "thumb": "img/thumb_06.png", "description": "面を取り除いたら、骨格だけ残った。" },
  { "num": "07", "title": "Floating Particles","tech": "three.js", "date": "2026-03-14", "path": "sketches/07_particles/",        "thumb": "img/thumb_07.png", "description": "3000個の点を空中に置いた。それぞれ勝手に動いている。" },
  { "num": "08", "title": "Morphing Mesh",     "tech": "three.js", "date": "2026-03-14", "path": "sketches/08_morph/",            "thumb": "img/thumb_08.png", "description": "球に揺らぎを与えたら、生き物みたいになった。" },
  { "num": "09", "title": "Ripple Plane",      "tech": "three.js", "date": "2026-03-14", "path": "sketches/09_ripple/",           "thumb": "img/thumb_09.png", "description": "平面に波を通した。クリックすると波紋が起きる。" },
  { "num": "10", "title": "Line Spiral",       "tech": "three.js", "date": "2026-03-14", "path": "sketches/10_spiral/",           "thumb": "img/thumb_10.png", "description": "コードがらせんを描いた。どこまでも伸びていく。" },
  { "num": "11", "title": "Noise Field",       "tech": "glsl",     "date": "2026-03-14", "path": "sketches/11_noise_field/",      "thumb": "img/thumb_11.png", "description": "ノイズに時間を足したら、霧みたいになった。" },
  { "num": "12", "title": "SDF Shapes",        "tech": "glsl",     "date": "2026-03-14", "path": "sketches/12_sdf_shapes/",       "thumb": "img/thumb_12.png", "description": "距離を測る関数だけで形を作った。線を引いていない。" },
  { "num": "13", "title": "Voronoi Lines",     "tech": "glsl",     "date": "2026-03-14", "path": "sketches/13_voronoi_lines/",    "thumb": "img/thumb_13.png", "description": "最近傍の点を探したら、領域の境目が現れた。" },
  { "num": "14", "title": "Interference",      "tech": "glsl",     "date": "2026-03-14", "path": "sketches/14_interference/",     "thumb": "img/thumb_14.png", "description": "波を重ねたら、重なった場所に縞が出てきた。" },
  { "num": "15", "title": "Fractal",           "tech": "glsl",     "date": "2026-03-14", "path": "sketches/15_fractal/",          "thumb": "img/thumb_15.png", "description": "同じ式を繰り返すだけで、際限なく細かくなる。" },
  { "num": "16", "title": "Voronoi",           "tech": "canvas",   "date": "2026-03-14", "path": "sketches/16_voronoi/",          "thumb": "img/thumb_16.png", "description": "最も近い点の境界を描いた。どの点も主役になれない。" },
  { "num": "17", "title": "L-System Tree",     "tech": "canvas",   "date": "2026-03-14", "path": "sketches/17_lsystem/",          "thumb": "img/thumb_17.png", "description": "1つのルールを繰り返したら、木になった。" },
  { "num": "18", "title": "Cellular Automata", "tech": "canvas",   "date": "2026-03-14", "path": "sketches/18_cellular/",         "thumb": "img/thumb_18.png", "description": "3つのルールだけで、世界が動き続けている。" },
  { "num": "19", "title": "Truchet Tiles",     "tech": "canvas",   "date": "2026-03-14", "path": "sketches/19_truchet/",          "thumb": "img/thumb_19.png", "description": "向きを変えただけで、繋がった。" },
  { "num": "20", "title": "Phyllotaxis",       "tech": "canvas",   "date": "2026-03-14", "path": "sketches/20_phyllotaxis/",      "thumb": "img/thumb_20.png", "description": "黄金角を繰り返したら、ひまわりみたいになった。" }
]
